ip_info_ye/__init__.py
ip_info_ye/test.py
ip_info_ye-0.1.dist-info/METADATA
ip_info_ye-0.1.dist-info/WHEEL
ip_info_ye-0.1.dist-info/top_level.txt
ip_info_ye-0.1.dist-info/RECORD
